[
    {
        "category": "Informatica",
        "question": "Cloud Computing:",
        "options": [
            "Erogazione di servizi di calcolo (server, storage, db) via internet (on-demand)",
            "Internet",
            "Server",
            "Nulla"
        ],
        "answer": "Erogazione di servizi di calcolo (server, storage, db) via internet (on-demand)"
    },
    {
        "category": "Informatica",
        "question": "IaaS (Infrastructure as a Service):",
        "options": [
            "Modello cloud dove si affittano risorse hardware virtualizzate (es. EC2)",
            "PaaS",
            "SaaS",
            "Nulla"
        ],
        "answer": "Modello cloud dove si affittano risorse hardware virtualizzate (es. EC2)"
    },
    {
        "category": "Informatica",
        "question": "PaaS (Platform as a Service):",
        "options": [
            "Modello cloud che fornisce piattaforma per sviluppare/deployare app (es. Heroku)",
            "IaaS",
            "SaaS",
            "Nulla"
        ],
        "answer": "Modello cloud che fornisce piattaforma per sviluppare/deployare app (es. Heroku)"
    },
    {
        "category": "Informatica",
        "question": "SaaS (Software as a Service):",
        "options": [
            "Modello cloud dove si usa software via web (es. Gmail, Office 365)",
            "IaaS",
            "PaaS",
            "Nulla"
        ],
        "answer": "Modello cloud dove si usa software via web (es. Gmail, Office 365)"
    },
    {
        "category": "Informatica",
        "question": "Serverless Computing:",
        "options": [
            "Modello di esecuzione dove il cloud provider gestisce dinamicamente le risorse (FaaS)",
            "Server",
            "Cloud",
            "Nulla"
        ],
        "answer": "Modello di esecuzione dove il cloud provider gestisce dinamicamente le risorse (FaaS)"
    },
    {
        "category": "Informatica",
        "question": "FaaS (Function as a Service):",
        "options": [
            "Eseguire singole funzioni in risposta a eventi senza gestire server (es. AWS Lambda)",
            "SaaS",
            "PaaS",
            "Nulla"
        ],
        "answer": "Eseguire singole funzioni in risposta a eventi senza gestire server (es. AWS Lambda)"
    },
    {
        "category": "Informatica",
        "question": "Virtualizzazione:",
        "options": [
            "Creare versioni virtuali di risorse fisiche (OS, server, storage)",
            "Cloud",
            "Emulazione",
            "Nulla"
        ],
        "answer": "Creare versioni virtuali di risorse fisiche (OS, server, storage)"
    },
    {
        "category": "Informatica",
        "question": "Containerization (Docker):",
        "options": [
            "Impacchettare app e dipendenze in container isolati (più leggeri delle VM)",
            "Virtualizzazione",
            "Cloud",
            "Nulla"
        ],
        "answer": "Impacchettare app e dipendenze in container isolati (più leggeri delle VM)"
    },
    {
        "category": "Informatica",
        "question": "Microservices Architecture:",
        "options": [
            "Architettura software composta da piccoli servizi indipendenti che comunicano via API",
            "Monolite",
            "SOA",
            "Nulla"
        ],
        "answer": "Architettura software composta da piccoli servizi indipendenti che comunicano via API"
    },
    {
        "category": "Informatica",
        "question": "Monolithic Architecture:",
        "options": [
            "Applicazione costruita come un'unica unità indivisibile",
            "Microservizi",
            "SOA",
            "Nulla"
        ],
        "answer": "Applicazione costruita come un'unica unità indivisibile"
    },
    {
        "category": "Informatica",
        "question": "DevOps:",
        "options": [
            "Insieme di pratiche che uniscono sviluppo (Dev) e operations (Ops) per rilasci rapidi",
            "Agile",
            "Scrum",
            "Nulla"
        ],
        "answer": "Insieme di pratiche che uniscono sviluppo (Dev) e operations (Ops) per rilasci rapidi"
    },
    {
        "category": "Informatica",
        "question": "Infrastructure as Code (IaC):",
        "options": [
            "Gestire l'infrastruttura tramite file di configurazione/codice (es. Terraform)",
            "DevOps",
            "Cloud",
            "Nulla"
        ],
        "answer": "Gestire l'infrastruttura tramite file di configurazione/codice (es. Terraform)"
    },
    {
        "category": "Informatica",
        "question": "Load Balancer:",
        "options": [
            "Distribuisce il traffico di rete tra più server per migliorare disponibilità e performance",
            "Proxy",
            "Router",
            "Nulla"
        ],
        "answer": "Distribuisce il traffico di rete tra più server per migliorare disponibilità e performance"
    },
    {
        "category": "Informatica",
        "question": "Scalabilità Orizzontale (Scale Out):",
        "options": [
            "Aggiungere più macchine al pool di risorse",
            "Scale Up",
            "Cloud",
            "Nulla"
        ],
        "answer": "Aggiungere più macchine al pool di risorse"
    },
    {
        "category": "Informatica",
        "question": "Scalabilità Verticale (Scale Up):",
        "options": [
            "Aggiungere più potenza (CPU, RAM) alla singola macchina esistente",
            "Scale Out",
            "Cloud",
            "Nulla"
        ],
        "answer": "Aggiungere più potenza (CPU, RAM) alla singola macchina esistente"
    },
    {
        "category": "Informatica",
        "question": "High Availability (HA):",
        "options": [
            "Sistema progettato per essere operativo per un'alta percentuale di tempo (99.999%)",
            "Disponibilità",
            "Affidabilità",
            "Nulla"
        ],
        "answer": "Sistema progettato per essere operativo per un'alta percentuale di tempo (99.999%)"
    },
    {
        "category": "Informatica",
        "question": "Fault Tolerance:",
        "options": [
            "Capacità di un sistema di continuare a funzionare anche in presenza di guasti",
            "HA",
            "Affidabilità",
            "Nulla"
        ],
        "answer": "Capacità di un sistema di continuare a funzionare anche in presenza di guasti"
    },
    {
        "category": "Informatica",
        "question": "Disaster Recovery:",
        "options": [
            "Piano e procedure per ripristinare l'infrastruttura IT dopo un disastro",
            "Backup",
            "Sicurezza",
            "Nulla"
        ],
        "answer": "Piano e procedure per ripristinare l'infrastruttura IT dopo un disastro"
    },
    {
        "category": "Informatica",
        "question": "Backup:",
        "options": [
            "Copia di sicurezza dei dati per prevenire perdite",
            "Salvataggio",
            "Copia",
            "Nulla"
        ],
        "answer": "Copia di sicurezza dei dati per prevenire perdite"
    },
    {
        "category": "Informatica",
        "question": "RTO (Recovery Time Objective):",
        "options": [
            "Tempo massimo accettabile per il ripristino di un servizio dopo un guasto",
            "RPO",
            "Tempo",
            "Nulla"
        ],
        "answer": "Tempo massimo accettabile per il ripristino di un servizio dopo un guasto"
    },
    {
        "category": "Informatica",
        "question": "RPO (Recovery Point Objective):",
        "options": [
            "Massima quantità di dati (misurata in tempo) che si può tollerare di perdere",
            "RTO",
            "Dati",
            "Nulla"
        ],
        "answer": "Massima quantità di dati (misurata in tempo) che si può tollerare di perdere"
    },
    {
        "category": "Informatica",
        "question": "Latenza:",
        "options": [
            "Tempo impiegato da un pacchetto dati per viaggiare dalla sorgente alla destinazione",
            "Ritardo",
            "Ping",
            "Nulla"
        ],
        "answer": "Tempo impiegato da un pacchetto dati per viaggiare dalla sorgente alla destinazione"
    },
    {
        "category": "Informatica",
        "question": "Bandwidth (Larghezza di banda):",
        "options": [
            "Quantità massima di dati trasmissibili in un dato tempo (bit/s)",
            "Velocità",
            "Rete",
            "Nulla"
        ],
        "answer": "Quantità massima di dati trasmissibili in un dato tempo (bit/s)"
    },
    {
        "category": "Informatica",
        "question": "Throughput:",
        "options": [
            "Quantità effettiva di dati trasmessi con successo in un dato tempo",
            "Bandwidth",
            "Velocità",
            "Nulla"
        ],
        "answer": "Quantità effettiva di dati trasmessi con successo in un dato tempo"
    },
    {
        "category": "Informatica",
        "question": "Jitter:",
        "options": [
            "Variazione nel ritardo di arrivo dei pacchetti (problema per VoIP/video)",
            "Latenza",
            "Rumore",
            "Nulla"
        ],
        "answer": "Variazione nel ritardo di arrivo dei pacchetti (problema per VoIP/video)"
    },
    {
        "category": "Informatica",
        "question": "Packet Loss:",
        "options": [
            "Percentuale di pacchetti persi durante la trasmissione",
            "Perdita",
            "Errore",
            "Nulla"
        ],
        "answer": "Percentuale di pacchetti persi durante la trasmissione"
    },
    {
        "category": "Informatica",
        "question": "Ping:",
        "options": [
            "Utility per testare la raggiungibilità di un host e misurare la latenza (RTT)",
            "Test",
            "Rete",
            "Nulla"
        ],
        "answer": "Utility per testare la raggiungibilità di un host e misurare la latenza (RTT)"
    },
    {
        "category": "Informatica",
        "question": "Traceroute:",
        "options": [
            "Utility per tracciare il percorso (hop) dei pacchetti verso una destinazione",
            "Trace",
            "Rete",
            "Nulla"
        ],
        "answer": "Utility per tracciare il percorso (hop) dei pacchetti verso una destinazione"
    },
    {
        "category": "Informatica",
        "question": "Wireshark:",
        "options": [
            "Analizzatore di protocolli di rete (packet sniffer) per troubleshooting",
            "Tool",
            "Rete",
            "Nulla"
        ],
        "answer": "Analizzatore di protocolli di rete (packet sniffer) per troubleshooting"
    },
    {
        "category": "Informatica",
        "question": "Nmap:",
        "options": [
            "Scanner di rete per scoprire host e servizi aperti (port scanning)",
            "Scanner",
            "Tool",
            "Nulla"
        ],
        "answer": "Scanner di rete per scoprire host e servizi aperti (port scanning)"
    },
    {
        "category": "Informatica",
        "question": "SSH (Secure Shell):",
        "options": [
            "Protocollo per accesso remoto sicuro a sistemi Unix/Linux (cifrato)",
            "Telnet",
            "FTP",
            "Nulla"
        ],
        "answer": "Protocollo per accesso remoto sicuro a sistemi Unix/Linux (cifrato)"
    },
    {
        "category": "Informatica",
        "question": "Telnet:",
        "options": [
            "Protocollo per accesso remoto non sicuro (testo in chiaro, obsoleto)",
            "SSH",
            "FTP",
            "Nulla"
        ],
        "answer": "Protocollo per accesso remoto non sicuro (testo in chiaro, obsoleto)"
    },
    {
        "category": "Informatica",
        "question": "FTP (File Transfer Protocol):",
        "options": [
            "Protocollo per trasferimento file (spesso non sicuro, meglio SFTP)",
            "HTTP",
            "SSH",
            "Nulla"
        ],
        "answer": "Protocollo per trasferimento file (spesso non sicuro, meglio SFTP)"
    },
    {
        "category": "Informatica",
        "question": "SFTP (SSH File Transfer Protocol):",
        "options": [
            "Trasferimento file sicuro su SSH",
            "FTP",
            "FTPS",
            "Nulla"
        ],
        "answer": "Trasferimento file sicuro su SSH"
    },
    {
        "category": "Informatica",
        "question": "SMTP (Simple Mail Transfer Protocol):",
        "options": [
            "Protocollo per invio email",
            "POP3",
            "IMAP",
            "Nulla"
        ],
        "answer": "Protocollo per invio email"
    },
    {
        "category": "Informatica",
        "question": "POP3 (Post Office Protocol 3):",
        "options": [
            "Protocollo per ricezione email (scarica e cancella dal server)",
            "IMAP",
            "SMTP",
            "Nulla"
        ],
        "answer": "Protocollo per ricezione email (scarica e cancella dal server)"
    },
    {
        "category": "Informatica",
        "question": "IMAP (Internet Message Access Protocol):",
        "options": [
            "Protocollo per ricezione email (sincronizza col server, lascia copia)",
            "POP3",
            "SMTP",
            "Nulla"
        ],
        "answer": "Protocollo per ricezione email (sincronizza col server, lascia copia)"
    },
    {
        "category": "Informatica",
        "question": "DHCP (Dynamic Host Configuration Protocol):",
        "options": [
            "Assegna automaticamente indirizzi IP e configurazioni ai dispositivi in rete",
            "DNS",
            "IP",
            "Nulla"
        ],
        "answer": "Assegna automaticamente indirizzi IP e configurazioni ai dispositivi in rete"
    },
    {
        "category": "Informatica",
        "question": "NAT (Network Address Translation):",
        "options": [
            "Tecnica per mappare indirizzi IP privati su un IP pubblico (risparmia IPv4)",
            "IP",
            "Rete",
            "Nulla"
        ],
        "answer": "Tecnica per mappare indirizzi IP privati su un IP pubblico (risparmia IPv4)"
    },
    {
        "category": "Informatica",
        "question": "Subnet Mask:",
        "options": [
            "Maschera che distingue la parte di rete e la parte host di un indirizzo IP",
            "IP",
            "Rete",
            "Nulla"
        ],
        "answer": "Maschera che distingue la parte di rete e la parte host di un indirizzo IP"
    },
    {
        "category": "Informatica",
        "question": "Gateway:",
        "options": [
            "Dispositivo (router) che collega reti diverse (punto di uscita verso internet)",
            "Router",
            "Switch",
            "Nulla"
        ],
        "answer": "Dispositivo (router) che collega reti diverse (punto di uscita verso internet)"
    },
    {
        "category": "Informatica",
        "question": "Switch:",
        "options": [
            "Dispositivo che collega dispositivi nella stessa rete locale (livello 2)",
            "Router",
            "Hub",
            "Nulla"
        ],
        "answer": "Dispositivo che collega dispositivi nella stessa rete locale (livello 2)"
    },
    {
        "category": "Informatica",
        "question": "Router:",
        "options": [
            "Dispositivo che instrada pacchetti tra reti diverse (livello 3)",
            "Switch",
            "Hub",
            "Nulla"
        ],
        "answer": "Dispositivo che instrada pacchetti tra reti diverse (livello 3)"
    },
    {
        "category": "Informatica",
        "question": "OSI Model:",
        "options": [
            "Modello di riferimento a 7 livelli per le telecomunicazioni (Fisico, Data Link, Network, Transport, Session, Presentation, Application)",
            "TCP/IP",
            "Modello",
            "Nulla"
        ],
        "answer": "Modello di riferimento a 7 livelli per le telecomunicazioni (Fisico, Data Link, Network, Transport, Session, Presentation, Application)"
    },
    {
        "category": "Informatica",
        "question": "TCP/IP Model:",
        "options": [
            "Modello a 4 livelli usato in internet (Link, Internet, Transport, Application)",
            "OSI",
            "Modello",
            "Nulla"
        ],
        "answer": "Modello a 4 livelli usato in internet (Link, Internet, Transport, Application)"
    },
    {
        "category": "Informatica",
        "question": "MAC Address:",
        "options": [
            "Indirizzo fisico univoco assegnato alla scheda di rete (48 bit)",
            "IP",
            "Indirizzo",
            "Nulla"
        ],
        "answer": "Indirizzo fisico univoco assegnato alla scheda di rete (48 bit)"
    },
    {
        "category": "Informatica",
        "question": "ARP (Address Resolution Protocol):",
        "options": [
            "Risolve indirizzi IP in indirizzi MAC",
            "DNS",
            "Rete",
            "Nulla"
        ],
        "answer": "Risolve indirizzi IP in indirizzi MAC"
    },
    {
        "category": "Informatica",
        "question": "ICMP (Internet Control Message Protocol):",
        "options": [
            "Protocollo per messaggi di errore e controllo (usato da Ping)",
            "TCP",
            "UDP",
            "Nulla"
        ],
        "answer": "Protocollo per messaggi di errore e controllo (usato da Ping)"
    },
    {
        "category": "Informatica",
        "question": "VLAN (Virtual LAN):",
        "options": [
            "Rete locale virtuale che segmenta una rete fisica in più reti logiche",
            "LAN",
            "Rete",
            "Nulla"
        ],
        "answer": "Rete locale virtuale che segmenta una rete fisica in più reti logiche"
    },
    {
        "category": "Informatica",
        "question": "Loopback Address (localhost):",
        "options": [
            "127.0.0.1 (indirizzo che punta alla macchina stessa)",
            "IP",
            "Rete",
            "Nulla"
        ],
        "answer": "127.0.0.1 (indirizzo che punta alla macchina stessa)"
    }
]