[
    {
        "id": "proc_pen_hard_1",
        "category": "Procedura Penale",
        "question": "L'incidente probatorio può essere richiesto:",
        "options": [
            "Nel corso delle indagini preliminari e nell'udienza preliminare",
            "Solo nel dibattimento",
            "Solo dalla persona offesa",
            "In qualsiasi stato e grado del processo"
        ],
        "answer": "Nel corso delle indagini preliminari e nell'udienza preliminare"
    },
    {
        "id": "proc_pen_hard_2",
        "category": "Procedura Penale",
        "question": "Le intercettazioni di conversazioni o comunicazioni sono consentite nei procedimenti per delitti non colposi per i quali è prevista la pena dell'ergastolo o della reclusione superiore nel massimo a:",
        "options": [
            "5 anni",
            "3 anni",
            "4 anni",
            "10 anni"
        ],
        "answer": "5 anni"
    },
    {
        "id": "proc_pen_hard_3",
        "category": "Procedura Penale",
        "question": "La nullità assoluta degli atti processuali:",
        "options": [
            "È insanabile e rilevabile d'ufficio in ogni stato e grado del procedimento",
            "È sanabile se non eccepita entro termini perentori",
            "Riguarda solo le notificazioni",
            "Può essere rilevata solo dalla parte interessata"
        ],
        "answer": "È insanabile e rilevabile d'ufficio in ogni stato e grado del procedimento"
    },
    {
        "id": "proc_pen_hard_4",
        "category": "Procedura Penale",
        "question": "Il giudizio abbreviato comporta, in caso di condanna, la diminuzione della pena:",
        "options": [
            "Di un terzo (o alla reclusione di anni 30 se prevista la pena dell'ergastolo)",
            "Della metà",
            "Di un sesto",
            "Di due terzi"
        ],
        "answer": "Di un terzo (o alla reclusione di anni 30 se prevista la pena dell'ergastolo)"
    },
    {
        "id": "proc_pen_hard_5",
        "category": "Procedura Penale",
        "question": "Il fermo di indiziato di delitto è disposto dal Pubblico Ministero quando:",
        "options": [
            "Sussistono specifici elementi che fanno ritenere fondato il pericolo di fuga e si procede per delitti gravi (limiti edittali specifici)",
            "Vi è flagranza di reato",
            "L'indagato confessa",
            "Non è possibile identificare l'indagato"
        ],
        "answer": "Sussistono specifici elementi che fanno ritenere fondato il pericolo di fuga e si procede per delitti gravi (limiti edittali specifici)"
    },
    {
        "id": "proc_pen_hard_6",
        "category": "Procedura Penale",
        "question": "La perquisizione domiciliare d'iniziativa della Polizia Giudiziaria è consentita:",
        "options": [
            "In caso di flagranza di reato o evasione, quando vi è fondato motivo di ritenere che cose o tracce pertinenti al reato si trovino in un determinato luogo",
            "Sempre, se autorizzata verbalmente dal Questore",
            "Solo per la ricerca di armi",
            "Mai senza decreto del PM"
        ],
        "answer": "In caso di flagranza di reato o evasione, quando vi è fondato motivo di ritenere che cose o tracce pertinenti al reato si trovino in un determinato luogo"
    },
    {
        "id": "proc_pen_hard_7",
        "category": "Procedura Penale",
        "question": "L'avviso di conclusione delle indagini preliminari (art. 415-bis c.p.p.) deve essere notificato:",
        "options": [
            "All'indagato e al suo difensore",
            "Solo all'indagato",
            "Solo al difensore",
            "Alla persona offesa"
        ],
        "answer": "All'indagato e al suo difensore"
    },
    {
        "id": "proc_pen_hard_8",
        "category": "Procedura Penale",
        "question": "La prova documentale è ammessa:",
        "options": [
            "Se rappresenta fatti, persone o cose mediante la fotografia, la cinematografia, la fonografia o qualsiasi altro mezzo",
            "Solo se si tratta di atti pubblici",
            "Solo se formata nel contraddittorio",
            "Mai nel rito abbreviato"
        ],
        "answer": "Se rappresenta fatti, persone o cose mediante la fotografia, la cinematografia, la fonografia o qualsiasi altro mezzo"
    },
    {
        "id": "proc_pen_hard_9",
        "category": "Procedura Penale",
        "question": "Il GIP (Giudice per le Indagini Preliminari) interviene:",
        "options": [
            "Su richiesta delle parti (PM o indagato/difensore) per emettere provvedimenti che incidono sulle libertà fondamentali o per l'archiviazione/rinvio a giudizio",
            "D'ufficio per dirigere le indagini",
            "Solo nel dibattimento",
            "Come organo dell'accusa"
        ],
        "answer": "Su richiesta delle parti (PM o indagato/difensore) per emettere provvedimenti che incidono sulle libertà fondamentali o per l'archiviazione/rinvio a giudizio"
    },
    {
        "id": "proc_pen_hard_10",
        "category": "Procedura Penale",
        "question": "L'inutilizzabilità delle prove (art. 191 c.p.p.) riguarda:",
        "options": [
            "Le prove acquisite in violazione dei divieti stabiliti dalla legge",
            "Le prove poco credibili",
            "Le prove non decisive",
            "Le prove raccolte senza la presenza del difensore (se non obbligatoria)"
        ],
        "answer": "Le prove acquisite in violazione dei divieti stabiliti dalla legge"
    }
]